django_sanitizers/__init__.py
django_sanitizers/middleware.py
django_sanitizers/sanitizer.py
django_sanitizers-0.0.1.dist-info/licenses/LICENSE
django_sanitizers-0.0.1.dist-info/METADATA
django_sanitizers-0.0.1.dist-info/WHEEL
django_sanitizers-0.0.1.dist-info/top_level.txt
django_sanitizers-0.0.1.dist-info/RECORD
