Metadata-Version: 2.4
Name: django-sanitizers
Version: 0.0.1
Summary: A Django middleware that sanitizes incoming request data to prevent XSS.
Author-email: Jenil Mistry <jenilmistryhq@users.noreply.github.com>
License: MIT License
Classifier: Programming Language :: Python :: 3
Classifier: Framework :: Django
Classifier: License :: OSI Approved :: MIT License
Classifier: Operating System :: OS Independent
Requires-Python: >=3.8
License-File: LICENSE
Requires-Dist: django>=3.2
Requires-Dist: bleach>=6.0.0
Dynamic: license-file
